cleantxty.py
cleantxty-0.0.5.dist-info/LICENSE
cleantxty-0.0.5.dist-info/METADATA
cleantxty-0.0.5.dist-info/WHEEL
cleantxty-0.0.5.dist-info/top_level.txt
cleantxty-0.0.5.dist-info/RECORD
