Metadata-Version: 2.1
Name: cleantxty
Version: 0.0.5
Summary: Python package to clean strings and making them reasonable for NLP
Home-page: UNKNOWN
Author: Tripathi Aditya Prakash
License: UNKNOWN
Platform: UNKNOWN
Classifier: Programming Language :: Python :: 3
Classifier: License :: OSI Approved :: MIT License
Classifier: Operating System :: OS Independent
Requires-Python: >=3.6
License-File: LICENSE
